{"status":200,"code":1000,"message":null,"timestamp":"1762294728283","path":null,"data":{"productCode":"AIAMACAU:WE2R","hot":false,"type":"BASIC","tags":null,"productName":"財富恆裕2霞壽險計劃","categoryCode":"LIFE","categoryName":"人壽","companyName":"友邦保險(澳門)","companyCode":"AIAMACAU","desc":"AIA深明您的人生規劃及需要會隨年月變改，為自己和摯愛作萬全準備，以應付無法預測的未來的重要性。「財富恆裕2」壽險計劃提供2個獨立計劃選項，透過不同程度的人壽保障，滿足您的需要。","fileTags":[],"files":[{"fileName":"財富恆裕2霞壽險計劃.pdf","filePath":"https://beefintech-centre.oss-accelerate.aliyuncs.com/PRODUCT/AIAMACAU/WE2R/財富恆裕2霞壽險計劃.pdf","uploadTime":1690166707268,"author":"BEEFINTECH-CENTRE","tags":null,"fileSize":null},{"fileName":"Wealth Elite 2 Ruby.pdf","filePath":"https://beefintech-centre.oss-accelerate.aliyuncs.com/PRODUCT/AIAMACAU/WE2R/Wealth Elite 2 Ruby.pdf","uploadTime":1690166710886,"author":"BEEFINTECH-CENTRE","tags":null,"fileSize":null}],"customFileTags":null,"customFiles":null,"medicalOptions":null,"logo":"https://lifebee.oss-accelerate.aliyuncs.com/ICON/insurer/aiamo.png","banner":null,"comparable":false,"quotable":false,"withdrawalable":false,"withdrawalOptions":null,"details":[{"key":"LIBasicInformation","name":"基本信息","nameI18n":{"zhHansCN":"基本信息","zhHantHK":"基本信息","enUS":"Basic Information","jaJP":null,"koKR":null},"rank":1,"attributes":[{"attribute":"LIBasicInformation_InterestOfAccumulationWithInterest","name":"儲存升息的利率","nameI18n":{"zhHansCN":"储存升息的利率","zhHantHK":"儲存升息的利率","enUS":"Interest of Accumulation with interest","jaJP":null,"koKR":null},"value":"-","valueI18n":null,"rank":1},{"attribute":"LIBasicInformation_BonusStructure","name":"紅利結構","nameI18n":{"zhHansCN":"红利结构","zhHantHK":"紅利結構","enUS":"Bonus Structure","jaJP":null,"koKR":null},"value":"-","valueI18n":null,"rank":2},{"attribute":"LIBasicInformation_AgeCalculationRules","name":"年齡計算規則","nameI18n":{"zhHansCN":"年龄计划规则","zhHantHK":"年齡計算規則","enUS":"Age Calculation Rules","jaJP":null,"koKR":null},"value":"-","valueI18n":null,"rank":3},{"attribute":"LIBasicInformation_AgeOfInsured","name":"受保人年齡","nameI18n":{"zhHansCN":"受保人年龄","zhHantHK":"受保人年齡","enUS":"Age of Insured","jaJP":null,"koKR":null},"value":"-","valueI18n":null,"rank":4},{"attribute":"LIBasicInformation_ProductFeatures","name":"產品特色","nameI18n":{"zhHansCN":"产品特色","zhHantHK":"產品特色","enUS":"Product Features","jaJP":null,"koKR":null},"value":"-","valueI18n":null,"rank":5},{"attribute":"LIBasicInformation_PaymentTerm","name":"繳費年期","nameI18n":{"zhHansCN":"供款年期","zhHantHK":"繳費年期","enUS":"Premium Term","jaJP":null,"koKR":null},"value":"-","valueI18n":null,"rank":6},{"attribute":"LIBasicInformation_AgeAtMaturity","name":"滿期年齡","nameI18n":{"zhHansCN":"满期年龄","zhHantHK":"滿期年齡","enUS":"Age at Maturity","jaJP":null,"koKR":null},"value":"-","valueI18n":null,"rank":7},{"attribute":"LIBasicInformation_PolicyCurrency","name":"保單幣別","nameI18n":{"zhHansCN":"保单币别","zhHantHK":"保單幣別","enUS":"Policy Currency","jaJP":null,"koKR":null},"value":"-","valueI18n":null,"rank":8},{"attribute":"LIBasicInformation_IsLifeInsuredChangeable","name":"是否可變更受保人","nameI18n":{"zhHansCN":"是否可变更受保人","zhHantHK":"是否可變更受保人","enUS":"Is life Insured changeable ","jaJP":null,"koKR":null},"value":"-","valueI18n":null,"rank":9},{"attribute":"LIBasicInformation_InvestmentStrategy","name":"投資策略","nameI18n":{"zhHansCN":"投资策略","zhHantHK":"投資策略","enUS":"Investment Strategy","jaJP":null,"koKR":null},"value":"-","valueI18n":null,"rank":10},{"attribute":"LIBasicInformation_InsuranceDeedExclusionsSuicide","name":"保險契約除外責任-自殺","nameI18n":{"zhHansCN":"保险契约除外责任-自杀","zhHantHK":"保險契約除外責任-自殺","enUS":"Insurance Deed Exclusions Suicide","jaJP":null,"koKR":null},"value":"-","valueI18n":null,"rank":11},{"attribute":"LIBasicInformation_GoverningLaw","name":"管轄法律","nameI18n":{"zhHansCN":"管辖法律","zhHantHK":"管轄法律","enUS":"Governing Law","jaJP":null,"koKR":null},"value":"-","valueI18n":null,"rank":12},{"attribute":"LIBasicInformation_InternationalFinancialRatingGradeS&P","name":"國際財務評定等級-標準普爾","nameI18n":{"zhHansCN":"国际财务评定等级-标准普尔","zhHantHK":"國際財務評定等級-標準普爾","enUS":"International Financial Rating Grade S&P","jaJP":null,"koKR":null},"value":"-","valueI18n":null,"rank":13}]},{"key":"LIChangeInsured","name":"更改受保人","nameI18n":{"zhHansCN":"更改受保人","zhHantHK":"更改受保人","enUS":"Change Insured","jaJP":null,"koKR":null},"rank":2,"attributes":[{"attribute":"LIChangeInsured_BenefitTerm","name":"保障年期","nameI18n":{"zhHansCN":"保障年期","zhHantHK":"保障年期","enUS":"Benefit Term","jaJP":null,"koKR":null},"value":"-","valueI18n":null,"rank":1},{"attribute":"LIChangeInsured_ExecutionPeriod","name":"行使期","nameI18n":{"zhHansCN":"行使期","zhHantHK":"行使期","enUS":"Execution Period","jaJP":null,"koKR":null},"value":"-","valueI18n":null,"rank":2},{"attribute":"LIChangeInsured_MaximumNumberOfChangeOfLifeInsured","name":"更換次數上限","nameI18n":{"zhHansCN":"更换次数上限","zhHantHK":"更換次數上限","enUS":"Maximum number of change of life inusred","jaJP":null,"koKR":null},"value":"-","valueI18n":null,"rank":3},{"attribute":"LIChangeInsured_InsurabilityOfContigentInsured","name":"新受保人資格","nameI18n":{"zhHansCN":"新受保人资格","zhHantHK":"新受保人資格","enUS":"Insurability of contigent insured","jaJP":null,"koKR":null},"value":"-","valueI18n":null,"rank":4},{"attribute":"LIChangeInsured_PhysicalPresentInHongKong","name":"是否來港","nameI18n":{"zhHansCN":"是否來港","zhHantHK":"是否來港","enUS":"Physical present in Hong Kong?","jaJP":null,"koKR":null},"value":"-","valueI18n":null,"rank":5},{"attribute":"LIChangeInsured_Supplement","name":"附加契約","nameI18n":{"zhHansCN":"附加契約","zhHantHK":"附加契約","enUS":"Supplement","jaJP":null,"koKR":null},"value":"-","valueI18n":null,"rank":6}]}],"currencies":["USD"],"frequencies":["SINGLE_PAYMENT"],"paymentTerm":["1"],"customPaymentTerm":null,"information":[{"id":4545,"title":"AIA(Macau):(更新)2025第四季度客戶推廣優惠","type":"PRODUCT_PROMOTION","time":1762245704667,"productCodes":["AIAMACAU:PUPMP","AIAMACAU:PUPMPR","AIAMACAU:OYS2","AIAMACAU:OYS2FG","AIAMACAU:EOYS","AIAMACAU:GFSIP","AIAMACAU:GPMCP3","AIAMACAU:WE2R","AIAMACAU:WE2S","AIAMACAU:SWP","AIAMACAU:SWPR"],"productNames":["尊耀明珠醫療計劃","尊耀明珠醫療計劃(附加計劃)","愛伴航保險計劃2","愛伴航-首護摯寶保險計劃2","簡緻·愛伴航保險計劃","環宇盈活儲蓄保險計劃","盈御多元貨幣計劃3","財富恆裕2霞壽險計劃","財富恆裕2蔚壽險計劃","睿選明珠醫療計劃","睿選明珠醫療計劃(附加計劃)"],"companyCode":"AIAMACAU","companyName":"友邦保險(澳門)","companyCodes":null,"companyNames":null,"tags":["友邦澳門"],"centreId":16040165901139968,"shareCount":5,"browseNumber":0,"browseCount":167,"endEffectiveDate":1767179093081},{"id":3914,"title":"AIA(Macau):(更新)2025第二季度客戶推廣優惠","type":"PRODUCT_PROMOTION","time":1746588966151,"productCodes":["AIAMACAU:PUPMP","AIAMACAU:OYS","AIAMACAU:OYSFG","AIA:BPV","AIAMACAU:GPMCP3","AIAMACAU:FASP","AIAMACAU:WE2S","AIAMACAU:WE2R"],"productNames":["尊耀明珠醫療計劃","愛伴航","愛伴航-首護摯寶","充裕未來‧盈尚","盈御多元貨幣計劃3","財富恆裕2蔚壽險計劃","財富恆裕2霞壽險計劃"],"companyCode":"AIAMACAU","companyName":"友邦保險(澳門)","companyCodes":null,"companyNames":null,"tags":["友邦澳門"],"centreId":14992627857686528,"shareCount":4,"browseNumber":0,"browseCount":205,"endEffectiveDate":1751281348578},{"id":2349,"title":"AIA(Macau):2023年第四季「AIA為您超越」推廣活動","type":"PRODUCT_PROMOTION","time":1696144897927,"productCodes":["AIAMACAU:AVS","AIAMACAU:AVF","AIAMACAU:AVP","AIAMACAU:CG3","AIAMACAU:CGP3","AIAMACAU:AA","AIAMACAU:OYS","AIAMACAU:OYSFG","AIAMACAU:PPMP","AIAMACAU:PPP","AIAMACAU:SGHP2","AIAMACAU:SGHR2","AIAMACAU:SP","AIAMACAU:WDTLP","AIAMACAU:WTLSC","AIAMACAU:ETLP","AIAMACAU:ETLPR","AIAMACAU:SCEP","AIAMACAU:SCE","AIAMACAU:AOAFP","AIAMACAU:AOACSIDP","AIAMACAU:BPV","AIAMACAU:GPMCP2","AIAMACAU:SLE5","AIAMACAU:SL","AIAMACAU:SLAD","AIAMACAU:FP2","AIAMACAU:WE2S","AIAMACAU:WE2R"],"productNames":["AIA自願醫保標準計劃","AIA自願醫保靈活計劃","AIA自願醫保尊尚計劃","癌症全方位保障3","癌症全方位明珠保障3","自在自選危疾保","愛伴航","愛伴航-首護摯寶","尊裕醫療計劃","尊裕明珠醫療計劃","特級健康之寶醫療保障計劃2","特級健康之寶住院及手術賠償附加契約2","銀意保","摯誠定期壽險計劃","摯誠定期壽險附加契約","尊誠定期壽險計劃","尊誠定期壽險(附加契約)","簡護危疾明珠保","簡護危疾保","AIA唯一摯保–全面保障","AIA唯一摯保明珠 - 全面保障","充裕未來‧盈尚","盈御多元貨幣計劃2","簡愛延續保障計劃5","樂怡人生保障計劃","樂怡人生保障計劃(週年紅利)","諾享保障計劃2","財富恆裕2蔚壽險計劃","財富恆裕2霞壽險計劃"],"companyCode":"AIAMACAU","companyName":"友邦保險(澳門)","companyCodes":null,"companyNames":null,"tags":["友邦澳門"],"centreId":11888515636985856,"shareCount":0,"browseNumber":0,"browseCount":0,"endEffectiveDate":1698731926778}],"proposalRiders":null,"quotationFieldRequirements":null,"features":{"maxWithdrawal":false,"hedgeable":false,"hedgeProducts":[],"coverageUrl":null,"highlights":[],"proposalAmountType":"BOTH","proposalAmountTip":null},"highlights":null,"proposalLanguages":["HK"],"proposalAmountType":"BOTH","proposalFrequencySupported":false,"custom":false,"reduceAmountTips":null,"premiumFinancingSupported":false,"ageRange":{"min":0,"max":128},"region":"澳門","dynamicFields":[],"proposalPrepaymentSupported":false,"proposalAmountTip":null,"sellStatus":"SELLING","isUpdate":false}}