{"status":200,"code":1000,"message":null,"timestamp":"1762296907330","path":null,"data":{"productCode":"BUPA:ESMEHISFT","hot":false,"type":"BASIC","tags":null,"productName":"保柏僱健康中小企醫療保障計劃(翺翔級別)","categoryCode":"GI","categoryName":"一般保險","companyName":"保柏(亞洲)","companyCode":"BUPA","desc":"","fileTags":[],"files":[{"fileName":"保柏僱健康中小企醫療保障計劃(翱翔級別).pdf","filePath":"https://beefintech-centre.oss-accelerate.aliyuncs.com/PRODUCT/BUPA/ESMEHISFT/保柏僱健康中小企醫療保障計劃(翱翔級別).pdf","uploadTime":1691722139014,"author":"BEEFINTECH-CENTRE","tags":null,"fileSize":null}],"customFileTags":null,"customFiles":null,"medicalOptions":{"regions":[],"deductibles":null,"levels":["PRIVATE","WARD","SEMI_PRIVATE"],"supplementaryBenefits":["DENTAL","SMM","MATERNITY"]},"logo":"https://lifebee.oss-accelerate.aliyuncs.com/ICON/insurer/bupa.png","banner":null,"comparable":false,"quotable":false,"withdrawalable":false,"withdrawalOptions":null,"details":null,"currencies":["HKD"],"frequencies":["ANNUALLY"],"paymentTerm":["~100"],"customPaymentTerm":null,"information":[{"id":4584,"title":"Bupa:Limited-time Promotion for Newly Enroled Clients","type":"PRODUCT_PROMOTION","time":1760420997140,"productCodes":["BUPA:ESMEHISST","BUPA:ESMEHISFT"],"productNames":["保柏僱健康中小企醫療保障計劃(啟航級別)","保柏僱健康中小企醫療保障計劃(翺翔級別)"],"companyCode":"BUPA","companyName":"保柏(亞洲)","companyCodes":null,"companyNames":null,"tags":["保柏"],"centreId":16100769936900096,"shareCount":2,"browseNumber":0,"browseCount":78,"endEffectiveDate":1769836031861}],"proposalRiders":null,"quotationFieldRequirements":null,"features":{"maxWithdrawal":false,"hedgeable":false,"hedgeProducts":[],"coverageUrl":null,"highlights":[],"proposalAmountType":"BOTH","proposalAmountTip":null},"highlights":null,"proposalLanguages":["HK"],"proposalAmountType":"BOTH","proposalFrequencySupported":false,"custom":false,"reduceAmountTips":null,"premiumFinancingSupported":false,"ageRange":{"min":0,"max":128},"region":"香港","dynamicFields":[],"proposalPrepaymentSupported":false,"proposalAmountTip":null,"sellStatus":"SELLING","isUpdate":false}}