{"status":200,"code":1000,"message":null,"timestamp":"1762670983951","path":null,"data":{"productCode":"GENERALI:OPI","hot":false,"type":"BASIC","tags":null,"productName":"辦公室綜合保險","categoryCode":"GI","categoryName":"一般保險","companyName":"忠意保險","companyCode":"GENERALIIS","desc":"辦公室綜合保險不但保費相宜，而且保障全面。除了基本財物保險外，還免費包括業務影響保險、金錢保險及公眾責任保險，使閣下的辦公室能在意外後迅速回復正常運作。","fileTags":[],"files":[{"fileName":"辦公室綜合保險.pdf","filePath":"https://beefintech-centre.oss-accelerate.aliyuncs.com/PRODUCT/GENERALI/OPI/辦公室綜合保險.pdf","uploadTime":1619054737042,"author":"BEEFINTECH-CENTRE","tags":null,"fileSize":null}],"customFileTags":null,"customFiles":null,"medicalOptions":null,"logo":"https://storage.lifebee.tech/ICON/insurer/generaliis.png","banner":null,"comparable":false,"quotable":false,"withdrawalable":false,"withdrawalOptions":null,"details":null,"currencies":["HKD"],"frequencies":["ANNUALLY"],"paymentTerm":["1"],"customPaymentTerm":null,"information":[],"proposalRiders":null,"quotationFieldRequirements":null,"features":{"maxWithdrawal":false,"hedgeable":false,"hedgeProducts":[],"coverageUrl":null,"highlights":[],"proposalAmountType":"BOTH","proposalAmountTip":null},"highlights":null,"proposalLanguages":["HK"],"proposalAmountType":"BOTH","proposalFrequencySupported":false,"custom":false,"reduceAmountTips":null,"premiumFinancingSupported":false,"ageRange":{"min":0,"max":128},"region":"香港","dynamicFields":[],"proposalPrepaymentSupported":false,"proposalAmountTip":null,"sellStatus":"SELLING","isUpdate":false}}