{"status":200,"code":1000,"message":null,"timestamp":"1762672213208","path":null,"data":{"productCode":"WALTON:SD","hot":false,"type":"BASIC","tags":null,"productName":"索迪山莊","categoryCode":"OTHERS","categoryName":"其他","companyName":"和頓國際集團","companyCode":"WALTON","desc":"項目索迪山莊 (Soddy Daisy) 坐落於美國田納西州東部漢密爾頓縣，地理位置優越。區內居民可經由27號高速公路，連接153號高速公路及75號州際公路便捷地通往查塔努加都會機場、諾克斯維爾、納什維爾 、亞特蘭大等周邊大城市。項目目前擬議作420套獨棟別墅住宅地塊的發展用途。","fileTags":[],"files":[{"fileName":"索迪山莊Soddy Daisy.pdf","filePath":"https://beefintech-centre.oss-accelerate.aliyuncs.com/PRODUCT/WALTON/SD/索迪山莊Soddy Daisy.pdf","uploadTime":1668586202504,"author":"BEEFINTECH-CENTRE","tags":null,"fileSize":null}],"customFileTags":null,"customFiles":null,"medicalOptions":null,"logo":"https://storage.lifebee.tech/ICON/insurer/walton.png","banner":null,"comparable":false,"quotable":false,"withdrawalable":false,"withdrawalOptions":null,"details":null,"currencies":["USD"],"frequencies":["SINGLE_PAYMENT"],"paymentTerm":["3"],"customPaymentTerm":null,"information":[],"proposalRiders":null,"quotationFieldRequirements":null,"features":{"maxWithdrawal":false,"hedgeable":false,"hedgeProducts":[],"coverageUrl":null,"highlights":[],"proposalAmountType":"BOTH","proposalAmountTip":null},"highlights":null,"proposalLanguages":["HK"],"proposalAmountType":"BOTH","proposalFrequencySupported":false,"custom":false,"reduceAmountTips":null,"premiumFinancingSupported":false,"ageRange":{"min":0,"max":128},"region":"香港","dynamicFields":[],"proposalPrepaymentSupported":false,"proposalAmountTip":null,"sellStatus":"SELLING","isUpdate":false}}