{"status":200,"code":1000,"message":null,"timestamp":"1762164669520","path":null,"data":{"id":112,"code":"BCT","name":"銀聯信託","logo":"https://lifebee.oss-accelerate.aliyuncs.com/ICON/insurer/bct.png","website":"https://www.bcthk.com/zh","links":[{"link":"https://www.bcthk.com/zh","description":"官網","descriptionI18n":{"zhHansCN":"官网","zhHantHK":"官網","enUS":"Official website","jaJP":null,"koKR":null},"addTime":null}],"desc":"銀聯信託有限公司是BCT銀聯集團的其中一間成員公司，為一間由多家本地金融機構於一九九九年組成的信託公司，為退休計劃和投資基金提供受託人、行政管理人及 / 或保管人服務，由其出任受託人的退休產品包括由銀聯金融有限公司（亦是BCT銀聯集團的成員公司）作保薦人的強積金集成信託計劃、行業計劃及匯集公積金計劃。公司亦為由第三者保薦的強積金 / 獨立公積金計劃及國際性退休計劃和環球投資基金，提供受託人、行政管理人及 / 或保管人服務。","banner":null,"files":[{"fileName":"銀聯信託 - 公司簡介 v202407.pdf","filePath":"https://beefintech-centre.oss-accelerate.aliyuncs.com/COMPANY/BCT/銀聯信託 - 公司簡介 v202407.pdf","uploadTime":1725524039126,"author":"BEEFINTECH-CENTRE","tags":["公司簡介"],"fileSize":3536691},{"fileName":"基於永久性地離開香港的理由而申索強積金累算權益的法定聲明  v202406.pdf","filePath":"https://beefintech-centre.oss-accelerate.aliyuncs.com/COMPANY/BCT/基於永久性地離開香港的理由而申索強積金累算權益的法定聲明  v202406.pdf","uploadTime":1756804316046,"author":"BEEFINTECH-CENTRE","tags":["表格 - 個人帳戶成員"],"fileSize":288180},{"fileName":"BCT 積金之選 - 個人帳戶成員申請表 v202501.pdf","filePath":"https://beefintech-centre.oss-accelerate.aliyuncs.com/COMPANY/BCT/BCT 積金之選 - 個人帳戶成員申請表 v202501.pdf","uploadTime":1756804316046,"author":"BEEFINTECH-CENTRE","tags":["表格 - 個人帳戶成員"],"fileSize":776524},{"fileName":"BCT 積金之選 - 更改投資指示表格（自僱人士╱個人帳戶成員） v202501.pdf","filePath":"https://beefintech-centre.oss-accelerate.aliyuncs.com/COMPANY/BCT/BCT 積金之選 - 更改投資指示表格（自僱人士╱個人帳戶成員） v202501.pdf","uploadTime":1756804316059,"author":"BEEFINTECH-CENTRE","tags":["表格 - 個人帳戶成員"],"fileSize":630196},{"fileName":"僱主更改資料表格 v202503.pdf","filePath":"https://beefintech-centre.oss-accelerate.aliyuncs.com/COMPANY/BCT/僱主更改資料表格 v202503.pdf","uploadTime":1756804399405,"author":"BEEFINTECH-CENTRE","tags":["表格 - 僱主"],"fileSize":735609},{"fileName":"反對附加費表格 v202406.pdf","filePath":"https://beefintech-centre.oss-accelerate.aliyuncs.com/COMPANY/BCT/反對附加費表格 v202406.pdf","uploadTime":1756804399405,"author":"BEEFINTECH-CENTRE","tags":["表格 - 僱主"],"fileSize":628205},{"fileName":"稅務居民身分自我證明 ( 控權人 ) v202503.pdf","filePath":"https://beefintech-centre.oss-accelerate.aliyuncs.com/COMPANY/BCT/稅務居民身分自我證明 ( 控權人 ) v202503.pdf","uploadTime":1756804399413,"author":"BEEFINTECH-CENTRE","tags":["表格 - 僱主"],"fileSize":614593},{"fileName":"終止受僱通知書 v202503.pdf","filePath":"https://beefintech-centre.oss-accelerate.aliyuncs.com/COMPANY/BCT/終止受僱通知書 v202503.pdf","uploadTime":1756804399415,"author":"BEEFINTECH-CENTRE","tags":["表格 - 僱主"],"fileSize":538915},{"fileName":"僱主資金轉移申請表 v202503.pdf","filePath":"https://beefintech-centre.oss-accelerate.aliyuncs.com/COMPANY/BCT/僱主資金轉移申請表 v202503.pdf","uploadTime":1756804399420,"author":"BEEFINTECH-CENTRE","tags":["表格 - 僱主"],"fileSize":533175},{"fileName":"工資組別申請╱更改表格 v202503.pdf","filePath":"https://beefintech-centre.oss-accelerate.aliyuncs.com/COMPANY/BCT/工資組別申請╱更改表格 v202503.pdf","uploadTime":1756804399421,"author":"BEEFINTECH-CENTRE","tags":["表格 - 僱主"],"fileSize":677654},{"fileName":"BCT 積金之選 - 自願性供款申請╱更改表格 v202501.pdf","filePath":"https://beefintech-centre.oss-accelerate.aliyuncs.com/COMPANY/BCT/BCT 積金之選 - 自願性供款申請╱更改表格 v202501.pdf","uploadTime":1756804399423,"author":"BEEFINTECH-CENTRE","tags":["表格 - 僱主"],"fileSize":1202112},{"fileName":"付款結算書 v202503.pdf","filePath":"https://beefintech-centre.oss-accelerate.aliyuncs.com/COMPANY/BCT/付款結算書 v202503.pdf","uploadTime":1756804399425,"author":"BEEFINTECH-CENTRE","tags":["表格 - 僱主"],"fileSize":781806},{"fileName":"強積金供款調整結算書 v202503.pdf","filePath":"https://beefintech-centre.oss-accelerate.aliyuncs.com/COMPANY/BCT/強積金供款調整結算書 v202503.pdf","uploadTime":1756804399428,"author":"BEEFINTECH-CENTRE","tags":["表格 - 僱主"],"fileSize":858240},{"fileName":"BCT 積金之選 - 僱主參與協議 v202501.pdf","filePath":"https://beefintech-centre.oss-accelerate.aliyuncs.com/COMPANY/BCT/BCT 積金之選 - 僱主參與協議 v202501.pdf","uploadTime":1756804399429,"author":"BEEFINTECH-CENTRE","tags":["表格 - 僱主"],"fileSize":1320243},{"fileName":"BCT 積金之選 - 成員登記表格 v202501.pdf","filePath":"https://beefintech-centre.oss-accelerate.aliyuncs.com/COMPANY/BCT/BCT 積金之選 - 成員登記表格 v202501.pdf","uploadTime":1756804399432,"author":"BEEFINTECH-CENTRE","tags":["表格 - 僱主"],"fileSize":806495},{"fileName":"稅務居民身分自我證明 ( 實體 ) v202503.pdf","filePath":"https://beefintech-centre.oss-accelerate.aliyuncs.com/COMPANY/BCT/稅務居民身分自我證明 ( 實體 ) v202503.pdf","uploadTime":1756804399434,"author":"BEEFINTECH-CENTRE","tags":["表格 - 僱主"],"fileSize":697424},{"fileName":"計劃成員可扣稅自願性供款轉移申請表 v202503.pdf","filePath":"https://beefintech-centre.oss-accelerate.aliyuncs.com/COMPANY/BCT/計劃成員可扣稅自願性供款轉移申請表 v202503.pdf","uploadTime":1756804509264,"author":"BEEFINTECH-CENTRE","tags":["可扣稅自願性供款帳戶持有人"],"fileSize":523557},{"fileName":"BCT 積金之選 - 可扣稅自願性供款帳戶成員申請表 v202501.pdf","filePath":"https://beefintech-centre.oss-accelerate.aliyuncs.com/COMPANY/BCT/BCT 積金之選 - 可扣稅自願性供款帳戶成員申請表 v202501.pdf","uploadTime":1756804509277,"author":"BEEFINTECH-CENTRE","tags":["可扣稅自願性供款帳戶持有人"],"fileSize":988181},{"fileName":"BCT 積金之選 - 特別自願性供款提取 ╱ 終止計劃表格 v202501.pdf","filePath":"https://beefintech-centre.oss-accelerate.aliyuncs.com/COMPANY/BCT/BCT 積金之選 - 特別自願性供款提取 ╱ 終止計劃表格 v202501.pdf","uploadTime":1756804523676,"author":"BEEFINTECH-CENTRE","tags":["特別自願性供款帳戶持有人"],"fileSize":487144},{"fileName":"BCT 積金之選 - 更改供款表格 v202501.pdf","filePath":"https://beefintech-centre.oss-accelerate.aliyuncs.com/COMPANY/BCT/BCT 積金之選 - 更改供款表格 v202501.pdf","uploadTime":1756804523677,"author":"BEEFINTECH-CENTRE","tags":["特別自願性供款帳戶持有人"],"fileSize":630227},{"fileName":"BCT 積金之選 - 直接付款授權 v202501.pdf","filePath":"https://beefintech-centre.oss-accelerate.aliyuncs.com/COMPANY/BCT/BCT 積金之選 - 直接付款授權 v202501.pdf","uploadTime":1756804523679,"author":"BEEFINTECH-CENTRE","tags":["特別自願性供款帳戶持有人"],"fileSize":475366},{"fileName":"BCT 積金之選 - 更改投資指示表格 ( 特別自願性供款帳戶成員╱可扣稅自願性供款帳戶成員 )  v202501.pdf","filePath":"https://beefintech-centre.oss-accelerate.aliyuncs.com/COMPANY/BCT/BCT 積金之選 - 更改投資指示表格 ( 特別自願性供款帳戶成員╱可扣稅自願性供款帳戶成員 )  v202501.pdf","uploadTime":1756804523679,"author":"BEEFINTECH-CENTRE","tags":["特別自願性供款帳戶持有人"],"fileSize":715008},{"fileName":"BCT 積金之選 - 特別自願性供款帳戶成員申請表 v202501.pdf","filePath":"https://beefintech-centre.oss-accelerate.aliyuncs.com/COMPANY/BCT/BCT 積金之選 - 特別自願性供款帳戶成員申請表 v202501.pdf","uploadTime":1756804523680,"author":"BEEFINTECH-CENTRE","tags":["特別自願性供款帳戶持有人"],"fileSize":956295},{"fileName":"聯繫公司╱更改業務擁有權之成員累算權益轉移表格 v202503.pdf","filePath":"https://beefintech-centre.oss-accelerate.aliyuncs.com/COMPANY/BCT/聯繫公司╱更改業務擁有權之成員累算權益轉移表格 v202503.pdf","uploadTime":1756804537219,"author":"BEEFINTECH-CENTRE","tags":["一般僱員/臨時僱員"],"fileSize":517886},{"fileName":"基於永久性地離開香港 ╱ 完全喪失行為能力 ╱ 罹患末期疾病 ╱ 小額結餘 ╱ 死亡的理由而申索強積金累算權益( 權益 )的表格 v202503.pdf","filePath":"https://beefintech-centre.oss-accelerate.aliyuncs.com/COMPANY/BCT/基於永久性地離開香港 ╱ 完全喪失行為能力 ╱ 罹患末期疾病 ╱ 小額結餘 ╱ 死亡的理由而申索強積金累算權益( 權益 )的表格 v202503.pdf","uploadTime":1756804537219,"author":"BEEFINTECH-CENTRE","tags":["一般僱員/臨時僱員"],"fileSize":763439},{"fileName":"對沖長期服務金╱遣散費之成員終止受僱通知書 v202504.pdf","filePath":"https://beefintech-centre.oss-accelerate.aliyuncs.com/COMPANY/BCT/對沖長期服務金╱遣散費之成員終止受僱通知書 v202504.pdf","uploadTime":1756804537220,"author":"BEEFINTECH-CENTRE","tags":["一般僱員/臨時僱員"],"fileSize":641955},{"fileName":"「僱員自選安排」— 轉移選擇表格 v202503.pdf","filePath":"https://beefintech-centre.oss-accelerate.aliyuncs.com/COMPANY/BCT/「僱員自選安排」— 轉移選擇表格 v202503.pdf","uploadTime":1756804537227,"author":"BEEFINTECH-CENTRE","tags":["一般僱員/臨時僱員"],"fileSize":578430},{"fileName":"終止受僱的法定聲明 v202311.pdf","filePath":"https://beefintech-centre.oss-accelerate.aliyuncs.com/COMPANY/BCT/終止受僱的法定聲明 v202311.pdf","uploadTime":1756804537229,"author":"BEEFINTECH-CENTRE","tags":["一般僱員/臨時僱員"],"fileSize":302020},{"fileName":"稅務居民身分自我證明 ( 個人 ) v202503.pdf","filePath":"https://beefintech-centre.oss-accelerate.aliyuncs.com/COMPANY/BCT/稅務居民身分自我證明 ( 個人 ) v202503.pdf","uploadTime":1756804537239,"author":"BEEFINTECH-CENTRE","tags":["一般僱員/臨時僱員"],"fileSize":677972},{"fileName":"BCT 積金之選 - 更改投資指示表格 ( 僱員 )  v202501.pdf","filePath":"https://beefintech-centre.oss-accelerate.aliyuncs.com/COMPANY/BCT/BCT 積金之選 - 更改投資指示表格 ( 僱員 )  v202501.pdf","uploadTime":1756804537243,"author":"BEEFINTECH-CENTRE","tags":["一般僱員/臨時僱員"],"fileSize":672993},{"fileName":"CT 積金之選 - 成員登記表格 v202501.pdf","filePath":"https://beefintech-centre.oss-accelerate.aliyuncs.com/COMPANY/BCT/CT 積金之選 - 成員登記表格 v202501.pdf","uploadTime":1756804537245,"author":"BEEFINTECH-CENTRE","tags":["一般僱員/臨時僱員"],"fileSize":806495},{"fileName":"基於小額結餘的理由而申索強積金累算權益的法定聲明 v202406.pdf","filePath":"https://beefintech-centre.oss-accelerate.aliyuncs.com/COMPANY/BCT/基於小額結餘的理由而申索強積金累算權益的法定聲明 v202406.pdf","uploadTime":1756804582785,"author":"BEEFINTECH-CENTRE","tags":["自僱人士"],"fileSize":302214},{"fileName":"成員永久不適合執行特定種類工作證明書 v202406.pdf","filePath":"https://beefintech-centre.oss-accelerate.aliyuncs.com/COMPANY/BCT/成員永久不適合執行特定種類工作證明書 v202406.pdf","uploadTime":1756804582787,"author":"BEEFINTECH-CENTRE","tags":["自僱人士"],"fileSize":180705},{"fileName":"基於提早退休的理由而申索強積金累算權益的法定聲明 v202406.pdf","filePath":"https://beefintech-centre.oss-accelerate.aliyuncs.com/COMPANY/BCT/基於提早退休的理由而申索強積金累算權益的法定聲明 v202406.pdf","uploadTime":1756804582789,"author":"BEEFINTECH-CENTRE","tags":["自僱人士"],"fileSize":151947},{"fileName":"成員罹患末期疾病的證明書 v202406.pdf","filePath":"https://beefintech-centre.oss-accelerate.aliyuncs.com/COMPANY/BCT/成員罹患末期疾病的證明書 v202406.pdf","uploadTime":1756804582790,"author":"BEEFINTECH-CENTRE","tags":["自僱人士"],"fileSize":258807},{"fileName":"成員更改資料表格 v202503.pdf","filePath":"https://beefintech-centre.oss-accelerate.aliyuncs.com/COMPANY/BCT/成員更改資料表格 v202503.pdf","uploadTime":1756804582792,"author":"BEEFINTECH-CENTRE","tags":["自僱人士"],"fileSize":599338},{"fileName":"第三方付款聲明表格 v202503.pdf","filePath":"https://beefintech-centre.oss-accelerate.aliyuncs.com/COMPANY/BCT/第三方付款聲明表格 v202503.pdf","uploadTime":1756804582792,"author":"BEEFINTECH-CENTRE","tags":["自僱人士"],"fileSize":508996},{"fileName":"基於已達到65歲退休年齡或提早退休的理由而申索強積金累算權益( 權益 )的表格 v202505.pdf","filePath":"https://beefintech-centre.oss-accelerate.aliyuncs.com/COMPANY/BCT/基於已達到65歲退休年齡或提早退休的理由而申索強積金累算權益( 權益 )的表格 v202505.pdf","uploadTime":1756804582842,"author":"BEEFINTECH-CENTRE","tags":["自僱人士"],"fileSize":742138},{"fileName":"計劃成員整合個人帳戶申請表 v202503.pdf","filePath":"https://beefintech-centre.oss-accelerate.aliyuncs.com/COMPANY/BCT/計劃成員整合個人帳戶申請表 v202503.pdf","uploadTime":1756804582843,"author":"BEEFINTECH-CENTRE","tags":["自僱人士"],"fileSize":548421},{"fileName":"計劃成員資金轉移申請表 v202503.pdf","filePath":"https://beefintech-centre.oss-accelerate.aliyuncs.com/COMPANY/BCT/計劃成員資金轉移申請表 v202503.pdf","uploadTime":1756804582843,"author":"BEEFINTECH-CENTRE","tags":["自僱人士"],"fileSize":639741},{"fileName":"資金來源聲明表格 v202503.pdf","filePath":"https://beefintech-centre.oss-accelerate.aliyuncs.com/COMPANY/BCT/資金來源聲明表格 v202503.pdf","uploadTime":1756804582845,"author":"BEEFINTECH-CENTRE","tags":["自僱人士"],"fileSize":409474},{"fileName":"基於永久性地離開香港 ╱ 完全喪失行為能力 ╱ 罹患末期疾病 ╱ 小額結餘 ╱ 死亡的理由而申索強積金累算權益的表格 v202503.pdf","filePath":"https://beefintech-centre.oss-accelerate.aliyuncs.com/COMPANY/BCT/基於永久性地離開香港 ╱ 完全喪失行為能力 ╱ 罹患末期疾病 ╱ 小額結餘 ╱ 死亡的理由而申索強積金累算權益的表格 v202503.pdf","uploadTime":1756804582847,"author":"BEEFINTECH-CENTRE","tags":["自僱人士"],"fileSize":763439},{"fileName":"由計劃成員的產業受託監管人就申索強積金累算權益所作的法定聲明 v202406.pdf","filePath":"https://beefintech-centre.oss-accelerate.aliyuncs.com/COMPANY/BCT/由計劃成員的產業受託監管人就申索強積金累算權益所作的法定聲明 v202406.pdf","uploadTime":1756804582847,"author":"BEEFINTECH-CENTRE","tags":["自僱人士"],"fileSize":391551},{"fileName":"稅務居民身分自我證明 ( 個人 )  v202503.pdf","filePath":"https://beefintech-centre.oss-accelerate.aliyuncs.com/COMPANY/BCT/稅務居民身分自我證明 ( 個人 )  v202503.pdf","uploadTime":1756804582847,"author":"BEEFINTECH-CENTRE","tags":["自僱人士"],"fileSize":677972},{"fileName":"最低強積金利益轉移申請表 － 獲強積金豁免的職業退休註冊計劃 v202503.pdf","filePath":"https://beefintech-centre.oss-accelerate.aliyuncs.com/COMPANY/BCT/最低強積金利益轉移申請表 － 獲強積金豁免的職業退休註冊計劃 v202503.pdf","uploadTime":1756804582848,"author":"BEEFINTECH-CENTRE","tags":["自僱人士"],"fileSize":516648},{"fileName":"終止計劃通知書 v202503.pdf","filePath":"https://beefintech-centre.oss-accelerate.aliyuncs.com/COMPANY/BCT/終止計劃通知書 v202503.pdf","uploadTime":1756804582849,"author":"BEEFINTECH-CENTRE","tags":["自僱人士"],"fileSize":518847},{"fileName":"基於永久性地離開香港的理由而申索強積金累算權益的法定聲明 v202406.pdf","filePath":"https://beefintech-centre.oss-accelerate.aliyuncs.com/COMPANY/BCT/基於永久性地離開香港的理由而申索強積金累算權益的法定聲明 v202406.pdf","uploadTime":1756804582849,"author":"BEEFINTECH-CENTRE","tags":["自僱人士"],"fileSize":288180},{"fileName":"AMTD強積金計劃 - 直接付款授權 v202501.pdf","filePath":"https://beefintech-centre.oss-accelerate.aliyuncs.com/COMPANY/BCT/AMTD強積金計劃 - 直接付款授權 v202501.pdf","uploadTime":1756804582854,"author":"BEEFINTECH-CENTRE","tags":["自僱人士"],"fileSize":475366},{"fileName":"自僱人士有關入息聲明及供款資料表格 v202503.pdf","filePath":"https://beefintech-centre.oss-accelerate.aliyuncs.com/COMPANY/BCT/自僱人士有關入息聲明及供款資料表格 v202503.pdf","uploadTime":1756804582854,"author":"BEEFINTECH-CENTRE","tags":["自僱人士"],"fileSize":548566},{"fileName":"BCT 積金之選 - 更改投資指示表格 ( 自僱人士╱個人帳戶成員 ) v202501.pdf","filePath":"https://beefintech-centre.oss-accelerate.aliyuncs.com/COMPANY/BCT/BCT 積金之選 - 更改投資指示表格 ( 自僱人士╱個人帳戶成員 ) v202501.pdf","uploadTime":1756804582855,"author":"BEEFINTECH-CENTRE","tags":["自僱人士"],"fileSize":630196},{"fileName":"BCT 積金之選 - 自僱人士自願性供款申請╱更改表格 v202501.pdf","filePath":"https://beefintech-centre.oss-accelerate.aliyuncs.com/COMPANY/BCT/BCT 積金之選 - 自僱人士自願性供款申請╱更改表格 v202501.pdf","uploadTime":1756804582855,"author":"BEEFINTECH-CENTRE","tags":["自僱人士"],"fileSize":583350},{"fileName":"BCT 積金之選 - 自僱人士申請表格 v202501.pdf","filePath":"https://beefintech-centre.oss-accelerate.aliyuncs.com/COMPANY/BCT/BCT 積金之選 - 自僱人士申請表格 v202501.pdf","uploadTime":1756804582856,"author":"BEEFINTECH-CENTRE","tags":["自僱人士"],"fileSize":1062861},{"fileName":"BCT 積金之選 - 成員自願性供款提取表格 v202501.pdf","filePath":"https://beefintech-centre.oss-accelerate.aliyuncs.com/COMPANY/BCT/BCT 積金之選 - 成員自願性供款提取表格 v202501.pdf","uploadTime":1756804582857,"author":"BEEFINTECH-CENTRE","tags":["自僱人士"],"fileSize":495111}],"fileTags":["公司簡介","表格 - 個人帳戶成員","表格 - 僱主","自僱人士","可扣稅自願性供款帳戶持有人","特別自願性供款帳戶持有人","一般僱員/臨時僱員"],"customFiles":null,"tags":null,"categories":[{"code":"SAVINGS","name":"儲蓄"},{"code":"LIFE","name":"人壽"},{"code":"ANNUITY","name":"年金"},{"code":"MEDICAL","name":"醫療"},{"code":"CRITICAL_ILLNESS","name":"危疾"},{"code":"TERM_LIFE","name":"定期壽險"},{"code":"ACCIDENT","name":"意外"},{"code":"UNIVERSAL_LIFE","name":"萬用壽險"},{"code":"INVESTMENT_LINKED","name":"投資相連"},{"code":"MPF","name":"強積金"},{"code":"GI","name":"一般保險"},{"code":"INDEX_UNIVERSAL_LIFE","name":"指數型萬用壽險"},{"code":"VARIABLE_UNIVERSAL_LIFE","name":"投資型萬用壽險"},{"code":"OTHERS","name":"其他"}],"products":[{"productCode":"BCT:BCTMPFPCSEP","productName":"BCT 積金之選 - 自僱人士","desc":"","categoryCode":"MPF","companyCode":"BCT","logo":"https://lifebee.oss-accelerate.aliyuncs.com/ICON/insurer/bct.png","rank":99,"hot":false,"categoryName":"強積金","quotationFieldRequirements":null,"sellStatus":"SELLING","isUpdate":false},{"productCode":"BCT:BCTMPFPCE","productName":"BCT 積金之選 - 僱主","desc":"","categoryCode":"MPF","companyCode":"BCT","logo":"https://lifebee.oss-accelerate.aliyuncs.com/ICON/insurer/bct.png","rank":99,"hot":false,"categoryName":"強積金","quotationFieldRequirements":null,"sellStatus":"SELLING","isUpdate":false},{"productCode":"BCT:BCTMPFPCPAM","productName":"BCT 積金之選 - 個人賬戶成員","desc":"","categoryCode":"MPF","companyCode":"BCT","logo":"https://lifebee.oss-accelerate.aliyuncs.com/ICON/insurer/bct.png","rank":99,"hot":false,"categoryName":"強積金","quotationFieldRequirements":null,"sellStatus":"SELLING","isUpdate":false},{"productCode":"BCT:BCTMPFPC","productName":"BCT積金之選(集成信託計劃)","desc":"","categoryCode":"MPF","companyCode":"BCT","logo":"https://lifebee.oss-accelerate.aliyuncs.com/ICON/insurer/bct.png","rank":99,"hot":false,"categoryName":"強積金","quotationFieldRequirements":null,"sellStatus":"SELLING","isUpdate":false},{"productCode":"BCT:BCTMPFIC","productName":"BCT(強積金)行業計劃","desc":"","categoryCode":"MPF","companyCode":"BCT","logo":"https://lifebee.oss-accelerate.aliyuncs.com/ICON/insurer/bct.png","rank":99,"hot":false,"categoryName":"強積金","quotationFieldRequirements":null,"sellStatus":"SELLING","isUpdate":false},{"productCode":"BCT:BCTPPORP","productName":"銀聯信託超卓匯集退休計劃","desc":"","categoryCode":"MPF","companyCode":"BCT","logo":"https://lifebee.oss-accelerate.aliyuncs.com/ICON/insurer/bct.png","rank":99,"hot":false,"categoryName":"強積金","quotationFieldRequirements":null,"sellStatus":"SELLING","isUpdate":false}],"exchangeRate":null,"exchangeRateUrl":null,"exchangeRateTime":null,"exchangeCurrency":null,"creditRatings":[],"region":"香港","documentInspectionTime":null,"levyRate":7.7973}}