{"status":200,"code":1000,"message":null,"timestamp":"1762172697186","path":null,"data":{"id":1933,"title":"Manulife:2023年5月至6月銷售推廣","type":"PRODUCT_PROMOTION","time":1683184510083,"tags":["宏利保險"],"content":"<p style=\"text-align: justify;\"><span style=\"font-size: 12pt; color: #000000; font-family: arial, helvetica, sans-serif;\">致合作夥伴：</span></p>\n<p style=\"text-align: justify;\"><span style=\"font-size: 12pt; color: #000000; font-family: arial, helvetica, sans-serif;\">&nbsp; &nbsp; &nbsp;&nbsp;為答謝各位對個人理財產品的一直支持，宏利保險欣然推出「2023年5月至6月銷售推廣」，推廣期為<span style=\"color: #ba372a;\"><strong>2023年5月2日至6月30日</strong></span>。</span></p>\n<p style=\"text-align: justify;\"><span style=\"font-size: 12pt; color: #000000; font-family: arial, helvetica, sans-serif;\">&nbsp; &nbsp; &nbsp; <span style=\"color: #843fa1;\"><strong>1.卓越終身保/優越終身保</strong></span></span></p>\n<ul style=\"text-align: justify;\">\n<li><span style=\"font-size: 12pt; color: #000000; font-family: arial, helvetica, sans-serif;\">首2個保單年度合共高達<span style=\"color: #169179;\"><strong>24%</strong></span>保費折扣優惠</span></li>\n</ul>\n<p style=\"text-align: justify;\"><span style=\"font-size: 12pt; color: #000000; font-family: arial, helvetica, sans-serif;\">&nbsp; &nbsp; &nbsp; <span style=\"color: #843fa1;\"><strong>2.精選定期壽險</strong></span></span></p>\n<ul style=\"text-align: justify;\">\n<li><span style=\"font-size: 12pt; color: #000000; font-family: arial, helvetica, sans-serif;\">首2個保單年度合共<span style=\"color: #169179;\"><strong>40%</strong></span>保費折扣優惠</span></li>\n</ul>\n<p style=\"text-align: justify;\"><span style=\"font-size: 12pt; color: #000000; font-family: arial, helvetica, sans-serif;\">&nbsp; &nbsp; &nbsp;<span style=\"color: #843fa1;\"><strong> 3.活耀人生危疾保2/活耀人生危疾保2(加強版)/心愛一家保/守護無間危疾保/守護無間危疾保(保寶未來)/悠然危疾保</strong></span></span></p>\n<ul style=\"text-align: justify;\">\n<li><span style=\"font-size: 12pt; color: #000000; font-family: arial, helvetica, sans-serif;\">首2個保單年度合共高達<span style=\"color: #169179;\"><strong>20%</strong></span>保費折扣優惠</span></li>\n</ul>\n<p style=\"text-align: justify;\"><span style=\"font-size: 12pt; color: #000000; font-family: arial, helvetica, sans-serif;\">&nbsp; &nbsp; &nbsp;<span style=\"color: #338ac1;\"><strong> <span style=\"color: #843fa1;\">4.宏利環球貨幣保障計劃</span></strong></span></span></p>\n<ul style=\"text-align: justify;\">\n<li><span style=\"font-size: 12pt; color: #000000; font-family: arial, helvetica, sans-serif;\">首2個保單年度合共高達<span style=\"color: #169179;\"><strong>24%</strong></span>保費折扣優惠</span></li>\n</ul>\n<p style=\"text-align: justify;\"><span style=\"font-size: 12pt; color: #000000; font-family: arial, helvetica, sans-serif;\">&nbsp; &nbsp; &nbsp; <span style=\"color: #843fa1;\"><strong>5.創富傳承保障計劃2</strong></span></span></p>\n<ul style=\"text-align: justify;\">\n<li><span style=\"font-size: 12pt; color: #000000; font-family: arial, helvetica, sans-serif;\">高達<span style=\"color: #169179;\"><strong>16%</strong></span>首年保費折扣優惠</span></li>\n</ul>\n<p style=\"text-align: justify;\"><span style=\"font-size: 12pt; color: #000000; font-family: arial, helvetica, sans-serif;\">&nbsp; &nbsp; &nbsp;<span style=\"color: #843fa1;\"> <strong>6.豐譽傳承保障計劃2</strong></span></span></p>\n<ul style=\"text-align: justify;\">\n<li><span style=\"font-size: 12pt; color: #000000; font-family: arial, helvetica, sans-serif;\">高達<span style=\"color: #169179;\"><strong>10%</strong></span>首年保費折扣優惠</span></li>\n</ul>\n<p style=\"text-align: justify;\"><span style=\"font-size: 12pt; color: #000000; font-family: arial, helvetica, sans-serif;\">&nbsp; &nbsp; &nbsp; <span style=\"color: #843fa1;\"><strong>7.赤霞珠終身壽險計劃2</strong></span></span></p>\n<ul style=\"text-align: justify;\">\n<li><span style=\"font-size: 12pt; color: #000000; font-family: arial, helvetica, sans-serif;\">首2個保單年度合共高達<span style=\"color: #169179;\"><strong>16%</strong></span>保費折扣優惠</span></li>\n</ul>\n<p style=\"text-align: justify;\"><span style=\"font-size: 12pt; color: #000000; font-family: arial, helvetica, sans-serif;\">&nbsp; &nbsp; &nbsp;<span style=\"color: #338ac1;\"><strong> <span style=\"color: #843fa1;\">8.世紀傳承保障計劃</span></strong></span></span></p>\n<ul style=\"text-align: justify;\">\n<li><span style=\"font-size: 12pt; color: #000000; font-family: arial, helvetica, sans-serif;\">首個保單年度高達<span style=\"color: #169179;\"><strong>20%</strong></span>保費折扣優惠</span></li>\n</ul>\n<p style=\"text-align: justify;\"><span style=\"font-size: 12pt; color: #000000; font-family: arial, helvetica, sans-serif;\">&nbsp; &nbsp; &nbsp; <span style=\"color: #843fa1;\"><strong>9.財摯家傳保障計劃</strong></span></span></p>\n<ul style=\"text-align: justify;\">\n<li><span style=\"font-size: 12pt; color: #000000; font-family: arial, helvetica, sans-serif;\">高達<span style=\"color: #169179;\"><strong>15%</strong></span>首年保費折扣優惠</span></li>\n</ul>\n<p style=\"text-align: justify;\"><span style=\"font-size: 12pt; color: #000000; font-family: arial, helvetica, sans-serif;\">&nbsp; &nbsp; &nbsp; <span style=\"color: #843fa1;\"><strong>10.財摯傳承保障計劃</strong></span></span></p>\n<ul style=\"text-align: justify;\">\n<li><span style=\"font-size: 12pt; color: #000000; font-family: arial, helvetica, sans-serif;\">高達<strong><span style=\"color: #169179;\">12%</span></strong>首年保費折扣優惠</span></li>\n</ul>\n<p style=\"text-align: justify;\"><span style=\"font-size: 12pt; font-family: arial, helvetica, sans-serif;\"><span style=\"color: #000000;\">&nbsp; &nbsp; &nbsp;<span style=\"color: #843fa1;\"><strong> 11.</strong></span></span><span style=\"color: #843fa1;\"><strong>萬用壽險</strong></span></span></p>\n<ul style=\"text-align: justify;\">\n<li><span style=\"color: #000000; font-size: 12pt; font-family: arial, helvetica, sans-serif;\"><strong><span style=\"color: #169179;\">3%</span></strong>初始按期保費折扣優惠</span></li>\n</ul>\n<p><span style=\"font-size: 12pt; font-family: arial, helvetica, sans-serif;\"><span style=\"color: #843fa1;\"><strong>&nbsp; &nbsp; &nbsp; 12.</strong></span><strong style=\"color: #843fa1; text-align: justify;\">指定自願醫保靈活計劃</strong></span></p>\n<ul style=\"text-align: justify;\">\n<li><span style=\"color: #000000; font-size: 12pt; font-family: arial, helvetica, sans-serif;\"><strong style=\"color: #843fa1; text-align: justify;\">宏利全護航自願醫保靈活計劃：</strong>高達首個保單年度享<span style=\"color: #169179;\"><strong>30%</strong></span>保費折扣優惠</span></li>\n<li><strong style=\"color: #843fa1; text-align: justify;\">宏利晉悅自願醫保靈活計劃：</strong>首個+第二個保單年度享<span style=\"color: #169179;\"><strong>40%</strong></span><span style=\"font-family: arial, helvetica, sans-serif; font-size: 16px;\">保費折扣優惠</span></li>\n</ul>\n<p><span style=\"font-size: 12pt; font-family: arial, helvetica, sans-serif;\"><span style=\"color: #000000;\"><strong>&nbsp; &nbsp; &nbsp;&nbsp;</strong></span><strong><span style=\"color: #843fa1;\">13.富足自主年金</span></strong><strong><span style=\"color: #843fa1;\">計劃</span></strong></span></p>\n<ul>\n<li><span style=\"font-size: 12pt; font-family: arial, helvetica, sans-serif;\">高達<span style=\"color: #169179;\"><strong>15%</strong></span>首年保費折扣優惠</span></li>\n</ul>\n<p><span style=\"font-size: 12pt; font-family: arial, helvetica, sans-serif;\"><span style=\"color: #000000;\"><strong>&nbsp; &nbsp; &nbsp; <span style=\"color: #843fa1;\">14.</span></strong></span><strong><span style=\"color: #843fa1;\">盈傳創富保障計劃2</span><span style=\"color: #ba372a; font-size: 10pt;\">(延長至2023年12月31日)</span></strong></span></p>\n<ul>\n<li><span style=\"font-family: arial, helvetica, sans-serif; font-size: 12pt;\"><span style=\"color: #169179;\"><strong>免費</strong></span>附加保障-身故賠償加強保</span></li>\n</ul>\n<p style=\"text-align: justify;\"><span style=\"font-size: 12pt; color: #000000; font-family: arial, helvetica, sans-serif;\">&nbsp; &nbsp; &nbsp;&nbsp;<span style=\"background-color: #ffffff; text-align: justify;\">詳情請參閱附件。</span></span></p>\n<p style=\"text-align: justify;\">&nbsp;</p>","attachments":[{"fileName":"NewsFlash.pdf","filePath":"https://beefintech-centre.oss-accelerate.aliyuncs.com/COMMON/2023-05-04/e5796184f4fa4f21994bccad2766592a.pdf","uploadTime":1683178764237,"author":"BEEFINTECH-CENTRE","tags":null,"fileSize":null},{"fileName":"赤霞珠終身壽險計劃2:世紀傳承保障計劃.pdf","filePath":"https://beefintech-centre.oss-accelerate.aliyuncs.com/COMMON/2023-05-04/eeb3dcb120a24336ba0334beee9c474f.pdf","uploadTime":1683179572512,"author":"BEEFINTECH-CENTRE","tags":null,"fileSize":null},{"fileName":"創富傳承保障計劃2.pdf","filePath":"https://beefintech-centre.oss-accelerate.aliyuncs.com/COMMON/2023-05-04/3a373082dfc64daa88d8f8d341e3f3ad.pdf","uploadTime":1683179572517,"author":"BEEFINTECH-CENTRE","tags":null,"fileSize":null},{"fileName":"財摯家傳保障計劃:財摯傳承保障計劃.pdf","filePath":"https://beefintech-centre.oss-accelerate.aliyuncs.com/COMMON/2023-05-04/fa9b3e72ac7240879a992e8ac5a8734c.pdf","uploadTime":1683179572517,"author":"BEEFINTECH-CENTRE","tags":null,"fileSize":null},{"fileName":"豐譽傳承保障計劃2.pdf","filePath":"https://beefintech-centre.oss-accelerate.aliyuncs.com/COMMON/2023-05-04/5b7b87fbf18243d5971133839e6f18a1.pdf","uploadTime":1683179572533,"author":"BEEFINTECH-CENTRE","tags":null,"fileSize":null},{"fileName":"雙倍優惠.pdf","filePath":"https://beefintech-centre.oss-accelerate.aliyuncs.com/COMMON/2023-05-04/5170c11845a347d99e09b0bb6453e7fd.pdf","uploadTime":1683179572534,"author":"BEEFINTECH-CENTRE","tags":null,"fileSize":null},{"fileName":"宏利環球貨幣保障計劃.pdf","filePath":"https://beefintech-centre.oss-accelerate.aliyuncs.com/COMMON/2023-05-04/b8758c5e8af24e35a71211887a2adf63.pdf","uploadTime":1683179572535,"author":"BEEFINTECH-CENTRE","tags":null,"fileSize":null},{"fileName":"萬用壽險.pdf","filePath":"https://beefintech-centre.oss-accelerate.aliyuncs.com/COMMON/2023-05-04/b89adfa10f9040369fe69d87dc45da6a.pdf","uploadTime":1683179572550,"author":"BEEFINTECH-CENTRE","tags":null,"fileSize":null},{"fileName":"指定自願醫保靈活計劃.pdf","filePath":"https://beefintech-centre.oss-accelerate.aliyuncs.com/COMMON/2023-05-04/f8d22bc2c63d4477ae1baeeeb05e0820.pdf","uploadTime":1683179572550,"author":"BEEFINTECH-CENTRE","tags":null,"fileSize":null}],"companyCode":"MANULIFE","companyName":"宏利保險","productCodes":["MANULIFE:MEP","MANULIFE:MANUPP","MANULIFE:MT","MANULIFE:MBC2","MANULIFE:MBC2P","MANULIFE:MLC","MANULIFE:MPRC","MANULIFE:MPRCBS","MANULIFE:MVC","MANULIFE:MGSA","MANULIFE:MPS2","MANULIFE:MGS2","MANULIFE:LV2","MANULIFE:MC","MANULIFE:PPS","MANULIFE:UL","MANULIFE:WIOP2","MANULIFE:FFAP"],"productNames":["卓越終身保","優越終身保","精選定期壽險","活耀人生危疾保2","活耀人生危疾保2(加強版)","心愛一家保","守護無間危疾保","守護無間危疾保(保寶未來)","悠然危疾保","宏利環球貨幣保障計劃","創富傳承保障計劃2","豐譽傳承保障計劃2","赤霞珠終身壽險計劃2","世紀傳承保障計劃","財摯家傳保障計劃","萬用壽險","盈傳創富保障計劃2","富足自主年金計劃"],"companyCodes":["MANULIFE"],"companyNames":["宏利保險"],"startEffectiveDate":1682998026299,"endEffectiveDate":1688095626311,"effective":false}}